Workbook

Sheet Costeo
A1: EcoSolar — Costeo de Productos de Instalación Fotovoltaica
A2: Proveedor: Bramanic SpA (Casablanca) · Precios netos transferencia (-4%) · Mayo 2026
A4: COMPONENTE | B4: BÁSICO 4.3kW | C4: MEDIO 8kW | D4: SUPERIOR 12kW
A5: EQUIPOS SOLARES
A6: Paneles Trina 720W (cant.) | B6: 6 | C6: 11 | D6: 17
A7: Precio panel c/u (transf.) | B7: 123840 | C7: 123840 | D7: 123840
A8: Subtotal paneles | B8: =B6*B7 -> 743040 | C8: =C6*C7 -> 1362240 | D8: =D6*D7 -> 2105280
A9: Inversor (transf.) | B9: 507840 | C9: 393600 | D9: 393600
A10: Estructuras montaje (transf.) | B10: 83424 | C10: 192528 | D10: 369744
A11: Batería litio (transf.) | B11: 747840 | C11: 1439040 | D11: 2878080
A12: BALANCE OF SYSTEM (BoS)
A13: Protecciones DC | B13: 27000 | C13: 41000 | D13: 55000
A14: Cables batería-inversor | B14: 28900 | C14: 32000 | D14: 64000
A15: Cable solar PV + MC4 | B15: 28200 | C15: 36900 | D15: 65100
A16: Tablero + protección AC + SPD* | B16: 60000 | C16: 80000 | D16: 110000
A17: Puesta a tierra* | B17: 25000 | C17: 30000 | D17: 40000
A18: COSTO EQUIPOS TOTAL | B18: =B8+B9+B10+B11+SUM(B13:B17) -> 2251244 | C18: =C8+C9+C10+C11+SUM(C13:C17) -> 3607308 | D18: =D8+D9+D10+D11+SUM(D13:D17) -> 6080804
A20: SUPUESTOS (editar celdas amarillas)
A21: Margen sobre equipos (%) | B21: 0.1 | C21: 0.1 | D21: 0.1
A22: Instalación sobre equipos (%) | B22: 0.2 | C22: 0.2 | D22: 0.2
A23: IVA (%) | B23: 0.19 | C23: 0.19 | D23: 0.19
A25: PRECIO DE VENTA
A26: Margen equipos ($) | B26: =B18*B21 -> 225124.4 | C26: =C18*C21 -> 360730.8 | D26: =D18*D21 -> 608080.4
A27: Instalación ($) | B27: =B18*B22 -> 450248.8 | C27: =C18*C22 -> 721461.6 | D27: =D18*D22 -> 1216160.8
A28: VENTA NETA | B28: =B18+B26+B27 -> 2926617.2 | C28: =C18+C26+C27 -> 4689500.4 | D28: =D18+D26+D27 -> 7905045.2
A29: IVA | B29: =B28*B23 -> 556057.27 | C29: =C28*C23 -> 891005.08 | D29: =D28*D23 -> 1501958.6
A30: PRECIO FINAL CON IVA | B30: =B28+B29 -> 3482674.5 | C30: =C28+C29 -> 5580505.5 | D30: =D28+D29 -> 9407003.8
A31: PRECIO PUBLICADO EN PÁGINA WEB | B31: 3490000 | C31: 5490000 | D31: 9490000
A32: Diferencia (publicado − calculado) | B32: =B31-B30 -> 7325.532 | C32: =C31-C30 -> -90505.476 | D32: =D31-D30 -> 82996.212
A34: * Tablero/protección AC y puesta a tierra no los surte Bramanic (otro proveedor eléctrico).

Sheet Equilibrio
A1: Punto de Equilibrio del Negocio
A3: CONCEPTO | B3: BÁSICO | C3: MEDIO | D3: SUPERIOR
A4: Margen equipos ($) | B4: =Costeo!B26 -> 225124.4 | C4: =Costeo!C26 -> 360730.8 | D4: =Costeo!D26 -> 608080.4
A5: Ingreso instalación ($) | B5: =Costeo!B27 -> 450248.8 | C5: =Costeo!C27 -> 721461.6 | D5: =Costeo!D27 -> 1216160.8
A6: (-) Costo real de instalar | B6: 300000 | C6: 300000 | D6: 300000
A7: UTILIDAD OPERACIONAL / VENTA | B7: =B4+B5-B6 -> 375373.2 | C7: =C4+C5-C6 -> 782192.4 | D7: =D4+D5-D6 -> 1524241.2
A9: Costos fijos mensuales | B9: 2000000
A11: ESCENARIO POR MIX DE VENTAS
A12: Mix de ventas (% por tier) | B12: 0.33333333 | C12: 0.33333333 | D12: 0.33333333
A13: Utilidad promedio ponderada / venta | B13: =B7*B12+C7*C12+D7*D12 -> 893935.6
A14: VENTAS/MES PARA EQUILIBRIO | B14: =B9/B13 -> 2.2372976
A15: (redondear hacia arriba a entero)
A17: EQUILIBRIO SI VENDES SOLO UN TIER
A18: Ventas/mes (un solo tier) | B18: =$B$9/B7 -> 5.3280309 | C18: =$B$9/C7 -> 2.5569157 | D18: =$B$9/D7 -> 1.3121283
A20: Edita las celdas amarillas (costo instalar, costos fijos, mix) y todo se recalcula.

Sheet Cámaras Ecoguard
A1: Ecoguard — Cámara Dahua Dual-Lens Solar PTZ 4G
A2: Costeo por unidad · IVA incluido · Mayo 2026
A4: INSUMOS (costo unitario)
A5: Cámara Dahua Dual-Lens Solar PTZ 4G | B5: 269900
A6: MicroSD 256GB | B6: 35000
A7: SIM de compañía (pago único) | B7: 4000
A8: COSTO INSUMOS TOTAL | B8: =SUM(B5:B7) -> 308900
A10: Costo poste 75×75 instalado | B10: 120000
A11: Costo real instalación (mano obra/transporte) | B11: 50000
A13: PRODUCTOS | B13: A · Estándar | C13: B · Con poste
A14: Precio de venta (IVA incl.) | B14: 490000 | C14: 690000
A15: (-) Costo insumos | B15: =-B8 -> -308900 | C15: =-B8 -> -308900
A16: (-) Costo poste | B16: 0 | C16: =-B10 -> -120000
A17: MARGEN BRUTO | B17: =SUM(B14:B16) -> 181100 | C17: =SUM(C14:C16) -> 261100
A18: (-) Costo instalación | B18: =-B11 -> -50000 | C18: =-B11 -> -50000
A19: UTILIDAD NETA / UNIDAD | B19: =B17+B18 -> 131100 | C19: =C17+C18 -> 211100
A20: Margen % sobre venta | B20: =B17/B14 -> 0.36959184 | C20: =C17/C14 -> 0.3784058
A22: Edita celdas amarillas (poste, instalación) y azules (precios). Margen % se calcula sobre margen bruto.
A23: Nota: con poste a $120k el margen % iguala al estándar. Subir precio B a ~$750k para mejor rentabilidad.
